htmsanity/__init__.py
htmsanity/nupic/__init__.py
htmsanity/nupic/journal.py
htmsanity/nupic/marshalling.py
htmsanity/nupic/model.py
htmsanity/nupic/runner.py
htmsanity/nupic/simulation.py
htmsanity/nupic/websocket.py
htmsanity/nupic/sanity/public/main.css
htmsanity/nupic/sanity/public/data/hotgym.consumption_weekend_hour.edn
htmsanity/nupic/sanity/public/demos/coordinates_2d.html
htmsanity/nupic/sanity/public/demos/cortical_io.html
htmsanity/nupic/sanity/public/demos/fixed_seqs.html
htmsanity/nupic/sanity/public/demos/hotgym.html
htmsanity/nupic/sanity/public/demos/letters.html
htmsanity/nupic/sanity/public/demos/q_learning_1d.html
htmsanity/nupic/sanity/public/demos/q_learning_2d.html
htmsanity/nupic/sanity/public/demos/runner.html
htmsanity/nupic/sanity/public/demos/second_level_motor.html
htmsanity/nupic/sanity/public/demos/sensorimotor_1d.html
htmsanity/nupic/sanity/public/demos/simple_sentences.html
htmsanity/nupic/sanity/public/demos/out/constants_table.js
htmsanity/nupic/sanity/public/demos/out/react.inc.js
htmsanity/nupic/sanity/public/demos/out/sanity.js
htmsanity/nupic/sanity/public/demos/out/sanity.js.map
htmsanity/nupic/sanity/public/demos/out/cljs/core.cljs
htmsanity/nupic/sanity/public/demos/out/cljs/core.js
htmsanity/nupic/sanity/public/demos/out/cljs/pprint.cljs
htmsanity/nupic/sanity/public/demos/out/cljs/pprint.js
htmsanity/nupic/sanity/public/demos/out/cljs/reader.cljs
htmsanity/nupic/sanity/public/demos/out/cljs/reader.js
htmsanity/nupic/sanity/public/demos/out/cljs/repl.cljs
htmsanity/nupic/sanity/public/demos/out/cljs/repl.js
htmsanity/nupic/sanity/public/demos/out/cljs/core/async.cljs
htmsanity/nupic/sanity/public/demos/out/cljs/core/async.js
htmsanity/nupic/sanity/public/demos/out/cljs/core/async/impl/buffers.cljs
htmsanity/nupic/sanity/public/demos/out/cljs/core/async/impl/buffers.js
htmsanity/nupic/sanity/public/demos/out/cljs/core/async/impl/channels.cljs
sanity_nupic-0.0.8.dist-info/DESCRIPTION.rst
sanity_nupic-0.0.8.dist-info/METADATA
sanity_nupic-0.0.8.dist-info/RECORD
sanity_nupic-0.0.8.dist-info/WHEEL
sanity_nupic-0.0.8.dist-info/metadata.json
sanity_nupic-0.0.8.dist-info/top_level.txt
