Metadata-Version: 2.0
Name: sanity-nupic
Version: 0.0.8
Summary: NuPIC server for Sanity client
Home-page: https://github.com/nupic-community/sanity-nupic/
Author: Marcus Lewis
Author-email: mrcslws@gmail.com
License: UNKNOWN
Platform: UNKNOWN
Requires-Dist: Twisted
Requires-Dist: autobahn
Requires-Dist: transit-python
